{
  "active": true,
  "address": "0xe9Cf7887b93150D4F2Da7dFc6D502B216438F244",
  "color": null,
  "decimals": 18,
  "description": [],
  "id": "f8831ce6-5e92-4389-8088-c6c46b697b36",
  "links": {
    "explorer": null,
    "research": null,
    "website": null,
    "github": null,
    "medium": null,
    "twitter": null,
    "reddit": null,
    "whitepaper": null
  },
  "logo": {
    "png": {
      "url": null,
      "ipfs": "ipfs://QmZcwn4eZJpjihH8TApRczQQJdAzpR6Er7g1bvo6PGhxWi"
    },
    "svg": {
      "url": null,
      "ipfs": null
    }
  },
  "name": "Uniswap sETH LP",
  "spam": false,
  "symbol": "UnisETHETH",
  "tags": [
    "unilpv1"
  ],
  "verifications": [],
  "version": {
    "major": 0,
    "minor": 0,
    "patch": 1
  }
}